recipeparser_kuronai/__init__.py
recipeparser_kuronai/recipe.py
recipeparser_kuronai/recipeutils.py
recipeparser_kuronai/urlutils.py
recipeparser_kuronai-0.0.6.dist-info/METADATA
recipeparser_kuronai-0.0.6.dist-info/WHEEL
recipeparser_kuronai-0.0.6.dist-info/licenses/LICENSE
recipeparser_kuronai-0.0.6.dist-info/RECORD
